{
  "buildNumber": "276",
  "buildId": "BdYYCv-Z",
  "sessionId": "P2QeoMsYc",
  "durationSec": 28.129,
  "avgFps": 38.005796347393535,
  "minFps": 32.168598108146696,
  "maxFps": 42.24570034076106,
  "avgSectionTimingsMs": {
    "hud": 0.02594059428366104,
    "camera": 0.0073267327676905265,
    "autoEngage": 0.0048538879807365,
    "syncPlayers": 0.11625371653331874,
    "syncUnits": 0.3336967296300251,
    "syncResources": 0.02636273522797614,
    "sendClientPoses": 0.06451932617764998,
    "effectsAndFog": 0.05916749279137527,
    "syncStructures": 0.23923444919038617
  },
  "userAgent": "Mozilla/5.0 (Linux; Android 10; K) AppleWebKit/537.36 (KHTML, like Gecko) Chrome/145.0.0.0 Mobile Safari/537.36",
  "timestamp": "2026-04-13T20:20:47.102Z"
}