{
  "buildNumber": "277",
  "buildId": "CMEduUks",
  "sessionId": "q0WoIYLvG",
  "durationSec": 39.449,
  "avgFps": 34.95667182261176,
  "minFps": 26.510727529094936,
  "maxFps": 39.361938941941844,
  "avgSectionTimingsMs": {
    "hud": 0.02237762220163353,
    "camera": 0.009712509596727575,
    "autoEngage": 0.00625728725738392,
    "syncPlayers": 0.0870139965697729,
    "syncUnits": 0.7591757388962187,
    "syncResources": 0.02636080852841515,
    "sendClientPoses": 0.07954898900692793,
    "effectsAndFog": 0.04961119756728272,
    "syncStructures": 0.1651724143274899
  },
  "userAgent": "Mozilla/5.0 (Linux; Android 10; K) AppleWebKit/537.36 (KHTML, like Gecko) Chrome/145.0.0.0 Mobile Safari/537.36",
  "timestamp": "2026-04-13T20:25:44.288Z"
}