{
  "buildNumber": "273",
  "buildId": "BF-xNiwv",
  "sessionId": "P_6xpY7hD",
  "durationSec": 61.217,
  "avgFps": 28.311820602811697,
  "minFps": 18.005645273948964,
  "maxFps": 40.321994488695054,
  "avgSectionTimingsMs": {
    "hud": 0.02632625995880729,
    "camera": 0.00802387261580409,
    "autoEngage": 0.005240464348895831,
    "syncPlayers": 0.08772395534395143,
    "syncUnits": 0.5763105506246741,
    "syncResources": 0.02700729920283484,
    "sendClientPoses": 0.11134704727958826,
    "effectsAndFog": 17.871400132646762,
    "syncStructures": 0.13333333352049767
  },
  "userAgent": "Mozilla/5.0 (Linux; Android 10; K) AppleWebKit/537.36 (KHTML, like Gecko) Chrome/145.0.0.0 Mobile Safari/537.36",
  "timestamp": "2026-04-13T20:02:58.106Z"
}