{
  "buildNumber": "275",
  "buildId": "DlwQSAVw",
  "sessionId": "7MiGiHpAI",
  "durationSec": 6.598,
  "avgFps": 18.340071921184748,
  "minFps": 15.453768091335075,
  "maxFps": 20.130142232611743,
  "avgSectionTimingsMs": {
    "hud": 0.024113476276397705,
    "camera": 0.010638297660976436,
    "autoEngage": 0.007829181240122513,
    "syncPlayers": 0.14357142810310636,
    "syncUnits": 1.1507142858845847,
    "syncStructures": 0.08124999888241291,
    "syncResources": 0.03642857096024922,
    "sendClientPoses": 0.21571428648063115,
    "effectsAndFog": 17.39500000008515
  },
  "userAgent": "Mozilla/5.0 (Linux; Android 10; K) AppleWebKit/537.36 (KHTML, like Gecko) Chrome/145.0.0.0 Mobile Safari/537.36",
  "timestamp": "2026-04-13T20:14:27.826Z"
}