{
  "buildNumber": "273",
  "buildId": "BF-xNiwv",
  "sessionId": "P_6xpY7hD",
  "durationSec": 22.845,
  "avgFps": 33.86314623288517,
  "minFps": 31.135007847593187,
  "maxFps": 40.321994488695054,
  "avgSectionTimingsMs": {
    "hud": 0.024386920989046955,
    "camera": 0.008446866387567338,
    "autoEngage": 0.0038173142223839216,
    "syncPlayers": 0.07517053229584375,
    "syncUnits": 0.03342428364337385,
    "syncResources": 0.028376534845461463,
    "sendClientPoses": 0.0055934516420793725,
    "effectsAndFog": 10.00900409235473,
    "syncStructures": 0.16445783085851784
  },
  "userAgent": "Mozilla/5.0 (Linux; Android 10; K) AppleWebKit/537.36 (KHTML, like Gecko) Chrome/145.0.0.0 Mobile Safari/537.36",
  "timestamp": "2026-04-13T20:02:19.734Z"
}