{
  "buildNumber": "276",
  "buildId": "BdYYCv-Z",
  "sessionId": "P2QeoMsYc",
  "durationSec": 0.032,
  "avgFps": 41.125914193165954,
  "minFps": 41.125914193165954,
  "maxFps": 41.125914193165954,
  "avgSectionTimingsMs": {
    "hud": 0.04999999701976776,
    "camera": 0,
    "autoEngage": 0.03333333134651184,
    "syncPlayers": 0.800000011920929,
    "syncUnits": 0.09999999403953552,
    "syncResources": 0.09999999403953552,
    "sendClientPoses": 0,
    "effectsAndFog": 0.5999999940395355
  },
  "userAgent": "Mozilla/5.0 (Linux; Android 10; K) AppleWebKit/537.36 (KHTML, like Gecko) Chrome/145.0.0.0 Mobile Safari/537.36",
  "timestamp": "2026-04-13T20:20:19.004Z"
}