{
  "buildNumber": "277",
  "buildId": "CMEduUks",
  "sessionId": "q0WoIYLvG",
  "durationSec": 28.87,
  "avgFps": 36.95376512268853,
  "minFps": 29.45054707312387,
  "maxFps": 39.361938941941844,
  "avgSectionTimingsMs": {
    "hud": 0.022939423877882743,
    "camera": 0.008440913427195695,
    "autoEngage": 0.005514158029433097,
    "syncPlayers": 0.08091451278026725,
    "syncUnits": 0.4216699804333048,
    "syncResources": 0.02584493029899673,
    "sendClientPoses": 0.050596421269725855,
    "effectsAndFog": 0.049801192718519134,
    "syncStructures": 0.20418604667796644
  },
  "userAgent": "Mozilla/5.0 (Linux; Android 10; K) AppleWebKit/537.36 (KHTML, like Gecko) Chrome/145.0.0.0 Mobile Safari/537.36",
  "timestamp": "2026-04-13T20:25:33.710Z"
}