{
  "buildNumber": "273",
  "buildId": "BF-xNiwv",
  "sessionId": "P_6xpY7hD",
  "durationSec": 47.08,
  "avgFps": 30.339763880941675,
  "minFps": 18.36505218394369,
  "maxFps": 40.321994488695054,
  "avgSectionTimingsMs": {
    "hud": 0.02591414948620364,
    "camera": 0.008028616776337495,
    "autoEngage": 0.005129224654457441,
    "syncPlayers": 0.08273667514371606,
    "syncUnits": 0.4770087509185621,
    "syncResources": 0.027605409625037474,
    "sendClientPoses": 0.07096260935423766,
    "effectsAndFog": 15.028321400106949,
    "syncStructures": 0.15136778146300273
  },
  "userAgent": "Mozilla/5.0 (Linux; Android 10; K) AppleWebKit/537.36 (KHTML, like Gecko) Chrome/145.0.0.0 Mobile Safari/537.36",
  "timestamp": "2026-04-13T20:02:43.969Z"
}