{
  "buildNumber": "277",
  "buildId": "CMEduUks",
  "sessionId": "q0WoIYLvG",
  "durationSec": 5.157,
  "avgFps": 38.46321604441044,
  "minFps": 38.293317991131715,
  "maxFps": 39.361938941941844,
  "avgSectionTimingsMs": {
    "hud": 0.021989528421332075,
    "camera": 0.0073298429631437935,
    "autoEngage": 0.0028871394048525594,
    "syncPlayers": 0.06842105247472462,
    "syncUnits": 0.028947368734761288,
    "syncResources": 0.025263157016352605,
    "sendClientPoses": 0.0015789472743084555,
    "effectsAndFog": 0.04157894645866595,
    "syncStructures": 0.17631579072851883
  },
  "userAgent": "Mozilla/5.0 (Linux; Android 10; K) AppleWebKit/537.36 (KHTML, like Gecko) Chrome/145.0.0.0 Mobile Safari/537.36",
  "timestamp": "2026-04-13T20:25:09.996Z"
}