{
  "buildNumber": "276",
  "buildId": "BdYYCv-Z",
  "sessionId": "P2QeoMsYc",
  "durationSec": 17.895,
  "avgFps": 39.80799377660673,
  "minFps": 36.559663552824205,
  "maxFps": 42.24570034076106,
  "avgSectionTimingsMs": {
    "hud": 0.0269399710315911,
    "camera": 0.006002928379863108,
    "autoEngage": 0.004688644627511719,
    "syncPlayers": 0.11055718489056808,
    "syncUnits": 0.18958944265793495,
    "syncResources": 0.02756598215998093,
    "sendClientPoses": 0.03489736080868852,
    "effectsAndFog": 0.05835777167176222,
    "syncStructures": 0.29699248120300753
  },
  "userAgent": "Mozilla/5.0 (Linux; Android 10; K) AppleWebKit/537.36 (KHTML, like Gecko) Chrome/145.0.0.0 Mobile Safari/537.36",
  "timestamp": "2026-04-13T20:20:36.867Z"
}