{
  "buildNumber": "276",
  "buildId": "BdYYCv-Z",
  "sessionId": "P2QeoMsYc",
  "durationSec": 25.974,
  "avgFps": 38.39806508518435,
  "minFps": 32.74417441448303,
  "maxFps": 42.24570034076106,
  "avgSectionTimingsMs": {
    "hud": 0.026694915525741495,
    "camera": 0.00730932210335287,
    "autoEngage": 0.005034446131949331,
    "syncPlayers": 0.1143160127063824,
    "syncUnits": 0.30137857924336975,
    "syncResources": 0.026511134550149217,
    "sendClientPoses": 0.05853658544802337,
    "effectsAndFog": 0.059384941928333594,
    "syncStructures": 0.2512953364787324
  },
  "userAgent": "Mozilla/5.0 (Linux; Android 10; K) AppleWebKit/537.36 (KHTML, like Gecko) Chrome/145.0.0.0 Mobile Safari/537.36",
  "timestamp": "2026-04-13T20:20:44.946Z"
}