{
  "buildNumber": "274",
  "buildId": "CB7E_Olw",
  "sessionId": "PJns0EXEj",
  "durationSec": 13.619,
  "avgFps": 44.91978434576329,
  "minFps": 41.91157244087777,
  "maxFps": 47.48005890965272,
  "avgSectionTimingsMs": {
    "hud": 0.01855670105141053,
    "camera": 0.006185567256101628,
    "autoEngage": 0.0032674118504889137,
    "syncPlayers": 0.08967297843524388,
    "syncUnits": 0.11841652310243367,
    "syncResources": 0.020137693816331084,
    "sendClientPoses": 0.023752151380923035,
    "effectsAndFog": 0.05370051597153669,
    "syncStructures": 0.3721153845007603
  },
  "userAgent": "Mozilla/5.0 (Linux; Android 10; K) AppleWebKit/537.36 (KHTML, like Gecko) Chrome/145.0.0.0 Mobile Safari/537.36",
  "timestamp": "2026-04-13T20:10:42.104Z"
}