{
  "buildNumber": "273",
  "buildId": "BF-xNiwv",
  "sessionId": "P_6xpY7hD",
  "durationSec": 5.455,
  "avgFps": 37.332382493434345,
  "minFps": 35.9435983015165,
  "maxFps": 40.321994488695054,
  "avgSectionTimingsMs": {
    "hud": 0.024607329780518696,
    "camera": 0.00732984265107759,
    "autoEngage": 0.002887139013745966,
    "syncPlayers": 0.06578947446848217,
    "syncUnits": 0.03315789479958384,
    "syncResources": 0.035263157988849436,
    "sendClientPoses": 0.003157894548616911,
    "effectsAndFog": 8.580526315381652,
    "syncStructures": 0.00731707273460016
  },
  "userAgent": "Mozilla/5.0 (Linux; Android 10; K) AppleWebKit/537.36 (KHTML, like Gecko) Chrome/145.0.0.0 Mobile Safari/537.36",
  "timestamp": "2026-04-13T20:02:02.345Z"
}