{
  "buildNumber": "276",
  "buildId": "BdYYCv-Z",
  "sessionId": "P2QeoMsYc",
  "durationSec": 9.416,
  "avgFps": 41.27398645194973,
  "minFps": 39.85117862344393,
  "maxFps": 42.24570034076106,
  "avgSectionTimingsMs": {
    "hud": 0.027631579182649912,
    "camera": 0.0060526316887453985,
    "autoEngage": 0.0031620553438214288,
    "syncPlayers": 0.10422163659161188,
    "syncUnits": 0.03562005229864397,
    "syncResources": 0.025857519584469555,
    "sendClientPoses": 0.001846965667754805,
    "effectsAndFog": 0.05488126691538929,
    "syncStructures": 0.3366197179740583
  },
  "userAgent": "Mozilla/5.0 (Linux; Android 10; K) AppleWebKit/537.36 (KHTML, like Gecko) Chrome/145.0.0.0 Mobile Safari/537.36",
  "timestamp": "2026-04-13T20:20:28.388Z"
}