{
  "buildNumber": "274",
  "buildId": "CB7E_Olw",
  "sessionId": "PJns0EXEj",
  "durationSec": 27.521,
  "avgFps": 41.42105146952369,
  "minFps": 31.92384310337146,
  "maxFps": 47.48005890965272,
  "avgSectionTimingsMs": {
    "hud": 0.018476190368334453,
    "camera": 0.008000000090826125,
    "autoEngage": 0.004478322999598924,
    "syncPlayers": 0.10066730252780497,
    "syncUnits": 0.5935176360368501,
    "syncResources": 0.020400381321220653,
    "sendClientPoses": 0.0833174451063427,
    "effectsAndFog": 0.05614871286686769,
    "syncStructures": 0.23495145619494243
  },
  "userAgent": "Mozilla/5.0 (Linux; Android 10; K) AppleWebKit/537.36 (KHTML, like Gecko) Chrome/145.0.0.0 Mobile Safari/537.36",
  "timestamp": "2026-04-13T20:10:56.007Z"
}