{
  "buildNumber": "275",
  "buildId": "DlwQSAVw",
  "sessionId": "7MiGiHpAI",
  "durationSec": 11.945,
  "avgFps": 19.81726946787536,
  "minFps": 15.453768091335075,
  "maxFps": 22.654334781660275,
  "avgSectionTimingsMs": {
    "hud": 0.01832061141501856,
    "camera": 0.010305343238452008,
    "autoEngage": 0.006883365189368136,
    "syncPlayers": 0.13026819923371646,
    "syncUnits": 0.957088122651038,
    "syncStructures": 0.08295454559001056,
    "syncResources": 0.03295019131967391,
    "sendClientPoses": 0.1888888888203778,
    "effectsAndFog": 16.712260536649676
  },
  "userAgent": "Mozilla/5.0 (Linux; Android 10; K) AppleWebKit/537.36 (KHTML, like Gecko) Chrome/145.0.0.0 Mobile Safari/537.36",
  "timestamp": "2026-04-13T20:14:33.173Z"
}