{
  "buildNumber": "276",
  "buildId": "BdYYCv-Z",
  "sessionId": "P2QeoMsYc",
  "durationSec": 48.428,
  "avgFps": 34.59145364259111,
  "minFps": 24.214324306218735,
  "maxFps": 42.24570034076106,
  "avgSectionTimingsMs": {
    "hud": 0.026092629026760093,
    "camera": 0.009849967380325855,
    "autoEngage": 0.006231647525681562,
    "syncPlayers": 0.14268929499636743,
    "syncUnits": 0.7473237601062648,
    "syncResources": 0.029112271400406838,
    "sendClientPoses": 0.115926892946501,
    "effectsAndFog": 0.06266318559257542,
    "syncStructures": 0.20168539278962638
  },
  "userAgent": "Mozilla/5.0 (Linux; Android 10; K) AppleWebKit/537.36 (KHTML, like Gecko) Chrome/145.0.0.0 Mobile Safari/537.36",
  "timestamp": "2026-04-13T20:21:07.400Z"
}