{
  "buildNumber": "273",
  "buildId": "BF-xNiwv",
  "sessionId": "P_6xpY7hD",
  "durationSec": 24.412,
  "avgFps": 33.73303900842488,
  "minFps": 31.135007847593187,
  "maxFps": 40.321994488695054,
  "avgSectionTimingsMs": {
    "hud": 0.02509603072220171,
    "camera": 0.008322663137763166,
    "autoEngage": 0.0035874439232781636,
    "syncPlayers": 0.07564102587027427,
    "syncUnits": 0.03358974353625224,
    "syncResources": 0.027307692361183654,
    "sendClientPoses": 0.005641025725083473,
    "effectsAndFog": 10.094999999533862,
    "syncStructures": 0.20505617910556578
  },
  "userAgent": "Mozilla/5.0 (Linux; Android 10; K) AppleWebKit/537.36 (KHTML, like Gecko) Chrome/145.0.0.0 Mobile Safari/537.36",
  "timestamp": "2026-04-13T20:02:21.302Z"
}